DBClient/DBClient.py
DBClient/__init__.py
pymongopandas-0.0.4.dist-info/LICENSE
pymongopandas-0.0.4.dist-info/METADATA
pymongopandas-0.0.4.dist-info/WHEEL
pymongopandas-0.0.4.dist-info/top_level.txt
pymongopandas-0.0.4.dist-info/RECORD
