Metadata-Version: 2.1
Name: pymongopandas
Version: 0.0.4
Summary: Wraps pymongo to easily interact with pandas dataframes
Home-page: https://github.com/JackFener/pymongo-pandas
Author: Giacomo Fava
Author-email: Giacomo Fava <giacomofava93@gmail.com>
Project-URL: Homepage, https://github.com/JackFener/pymongo-pandas
Project-URL: Bug Tracker, https://github.com/JackFener/pymongo-pandas/issues
Classifier: Programming Language :: Python :: 3
Classifier: License :: OSI Approved :: MIT License
Classifier: Operating System :: OS Independent
Requires-Python: >=3.7
License-File: LICENSE
